cnf/__init__.py
cnf/files.py
cnf/filter.py
cnf/functions.py
cnf/print.py
cnf-0.0.4.dist-info/LICENSE
cnf-0.0.4.dist-info/METADATA
cnf-0.0.4.dist-info/WHEEL
cnf-0.0.4.dist-info/top_level.txt
cnf-0.0.4.dist-info/RECORD
