Metadata-Version: 2.1
Name: cnf
Version: 0.0.4
Summary: Simple Conjunctive Normal Filter for python3
Home-page: https://gitlab.com/SumNeuron/cnf
Author: Sumner Magruder
Author-email: sumner.magruder@zmnh.uni-hamburg.de
License: UNKNOWN
Platform: UNKNOWN
Classifier: Programming Language :: Python :: 3.5
Classifier: License :: OSI Approved :: MIT License
Classifier: Operating System :: OS Independent
